pysolarmanv5/__init__.py
pysolarmanv5/pysolarmanv5.py
pysolarmanv5/pysolarmanv5_async.py
pysolarmanv5-3.0.5.dist-info/LICENSE
pysolarmanv5-3.0.5.dist-info/METADATA
pysolarmanv5-3.0.5.dist-info/WHEEL
pysolarmanv5-3.0.5.dist-info/top_level.txt
pysolarmanv5-3.0.5.dist-info/RECORD
