Metadata-Version: 2.1
Name: pysolarmanv5
Version: 3.0.5
Summary: A Python library for interacting with Solarman (IGEN-Tech) v5 based Solar Data Loggers
Author-email: Jonathan McCrohan <jmccrohan@gmail.com>
License: MIT License
Project-URL: homepage, https://github.com/jmccrohan/pysolarmanv5
Project-URL: repository, https://github.com/jmccrohan/pysolarmanv5
Project-URL: documentation, https://pysolarmanv5.readthedocs.io/
Project-URL: changelog, https://pysolarmanv5.readthedocs.io/en/latest/changelog.html
Keywords: solarman,igen-tech,modbus,solar,inverter,solarmanv5
Classifier: Programming Language :: Python :: 3
Classifier: Topic :: Utilities
Classifier: License :: OSI Approved :: MIT License
Requires-Python: >=3.8
License-File: LICENSE
Requires-Dist: umodbus
Provides-Extra: dev
Requires-Dist: build; extra == "dev"
Requires-Dist: twine; extra == "dev"
Requires-Dist: black; extra == "dev"
Requires-Dist: pylint; extra == "dev"
Requires-Dist: pytest; extra == "dev"
